{
  "project_info": {
    "project_number": "618381183914",
    "firebase_url": "https://unito-app.firebaseio.com",
    "project_id": "unito-app",
    "storage_bucket": "unito-app.appspot.com"
  },
  "client": [
    {
      "client_info": {
        "mobilesdk_app_id": "1:618381183914:android:be594e85cdd2b642e479d3",
        "android_client_info": {
          "package_name": "dot.studios.unito"
        }
      },
      "oauth_client": [
        {
          "client_id": "618381183914-cdjndebtago9u95ji4jvma7as60q2qoh.apps.googleusercontent.com",
          "client_type": 1,
          "android_info": {
            "package_name": "dot.studios.unito",
            "certificate_hash": "7313b6787a58fa26cc101b2ac1241fdb60e89b4f"
          }
        },
        {
          "client_id": "618381183914-m45j54n2pqr158iatcu4nh06snpk15m7.apps.googleusercontent.com",
          "client_type": 3
        }
      ],
      "api_key": [
        {
          "current_key": "AIzaSyDuaMNeKO5cZNPt3xYs-Yb2Lxv598qsXG8"
        }
      ],
      "services": {
        "appinvite_service": {
          "other_platform_oauth_client": [
            {
              "client_id": "618381183914-m45j54n2pqr158iatcu4nh06snpk15m7.apps.googleusercontent.com",
              "client_type": 3
            }
          ]
        }
      }
    }
  ],
  "configuration_version": "1"
}